TonieToolbox/__init__.py
TonieToolbox/__main__.py
TonieToolbox/artwork.py
TonieToolbox/audio_conversion.py
TonieToolbox/constants.py
TonieToolbox/dependency_manager.py
TonieToolbox/filename_generator.py
TonieToolbox/integration.py
TonieToolbox/integration_macos.py
TonieToolbox/integration_ubuntu.py
TonieToolbox/integration_windows.py
TonieToolbox/logger.py
TonieToolbox/media_tags.py
TonieToolbox/ogg_page.py
TonieToolbox/opus_packet.py
TonieToolbox/recursive_processor.py
TonieToolbox/tags.py
TonieToolbox/teddycloud.py
TonieToolbox/tonie_analysis.py
TonieToolbox/tonie_file.py
TonieToolbox/tonie_header.proto
TonieToolbox/tonie_header_pb2.py
TonieToolbox/tonies_json.py
TonieToolbox/version_handler.py
tonietoolbox-0.6.1.dist-info/licenses/LICENSE.md
tonietoolbox-0.6.1.dist-info/METADATA
tonietoolbox-0.6.1.dist-info/WHEEL
tonietoolbox-0.6.1.dist-info/entry_points.txt
tonietoolbox-0.6.1.dist-info/top_level.txt
tonietoolbox-0.6.1.dist-info/RECORD
