Metadata-Version: 2.4
Name: TonieToolbox
Version: 0.6.1
Summary: Convert audio files to Toniebox compatible format (.TAF) and interact with TeddyCloud.
Home-page: https://github.com/Quentendo64/TonieToolbox
Author: Quentendo64
Author-email: Quentendo64 <quentin@wohlfeil.at>
License-Expression: GPL-3.0-or-later
Project-URL: Homepage, https://github.com/Quentendo64/TonieToolbox
Project-URL: Bug Tracker, https://github.com/Quentendo64/TonieToolbox/issues
Classifier: Programming Language :: Python :: 3
Classifier: Programming Language :: Python :: 3.6
Classifier: Programming Language :: Python :: 3.7
Classifier: Programming Language :: Python :: 3.8
Classifier: Programming Language :: Python :: 3.9
Classifier: Programming Language :: Python :: 3.10
Classifier: Operating System :: OS Independent
Classifier: Topic :: Multimedia :: Sound/Audio :: Conversion
Requires-Python: >=3.6
License-File: LICENSE.md
Requires-Dist: protobuf<=3.19.0
Requires-Dist: requests>=2.32.3
Requires-Dist: mutagen>=1.47.0
Requires-Dist: packaging>=25.0
Requires-Dist: tqdm>=4.67.1
Provides-Extra: test
Requires-Dist: pytest>=8.3.5; extra == "test"
Requires-Dist: pytest-cov>=6.1.1; extra == "test"
Dynamic: author
Dynamic: home-page
Dynamic: license-file
Dynamic: requires-python
